parakeet_mlx/__init__.py
parakeet_mlx/alignment.py
parakeet_mlx/attention.py
parakeet_mlx/audio.py
parakeet_mlx/cache.py
parakeet_mlx/cli.py
parakeet_mlx/conformer.py
parakeet_mlx/ctc.py
parakeet_mlx/parakeet.py
parakeet_mlx/rnnt.py
parakeet_mlx/tokenizer.py
parakeet_mlx/utils.py
parakeet_mlx-0.5.0.dist-info/licenses/LICENSE
parakeet_mlx-0.5.0.dist-info/METADATA
parakeet_mlx-0.5.0.dist-info/WHEEL
parakeet_mlx-0.5.0.dist-info/entry_points.txt
parakeet_mlx-0.5.0.dist-info/top_level.txt
parakeet_mlx-0.5.0.dist-info/RECORD
