Metadata-Version: 2.4
Name: parakeet-mlx
Version: 0.5.0
Summary: An implementation of the Nvidia's Parakeet models for Apple Silicon using MLX.
License-Expression: Apache-2.0
Project-URL: Repository, https://github.com/senstella/parakeet-mlx.git
Project-URL: Issues, https://github.com/senstella/parakeet-mlx/issues
Keywords: mlx,parakeet,asr,nvidia,apple,speech,recognition,ml
Requires-Python: >=3.10
License-File: LICENSE
Requires-Dist: dacite>=1.9.2
Requires-Dist: huggingface-hub>=0.30.2
Requires-Dist: librosa>=0.11.0
Requires-Dist: mlx>=0.22.1
Requires-Dist: numpy>=2.2.5
Requires-Dist: typer>=0.15.3
Dynamic: license-file
